llmbot_plugin_reecho_voice/__init__.py
llmbot_plugin_reecho_voice/request.py
llmbot_plugin_reecho_voice-0.0.4.dist-info/LICENSE
llmbot_plugin_reecho_voice-0.0.4.dist-info/METADATA
llmbot_plugin_reecho_voice-0.0.4.dist-info/WHEEL
llmbot_plugin_reecho_voice-0.0.4.dist-info/entry_points.txt
llmbot_plugin_reecho_voice-0.0.4.dist-info/RECORD
