Metadata-Version: 2.1
Name: llmbot_plugin_reecho_voice
Version: 0.0.4
Summary: Generate Voice From reecho.ai Api In OpenAiBot.
License: MIT
Author: LlmKira
Author-email: me@dianas.cyou
Requires-Python: >=3.8,<4.0
Classifier: License :: OSI Approved :: MIT License
Classifier: Programming Language :: Python :: 3
Classifier: Programming Language :: Python :: 3.8
Classifier: Programming Language :: Python :: 3.9
Classifier: Programming Language :: Python :: 3.10
Classifier: Programming Language :: Python :: 3.11
Classifier: Programming Language :: Python :: 3.12
Project-URL: Documentation, https://dev.reecho.ai/generate/sync
